muninn/__init__.py
muninn/auth.py
muninn/formatting.py
muninn/version.py
muninn/client/__init__.py
muninn/client/authenticate.py
muninn/client/cleanup.py
muninn/client/create.py
muninn/client/data.py
muninn/client/events.py
muninn/client/gpus.py
muninn/client/logs.py
muninn/client/ping.py
muninn/client/push.py
muninn/client/run.py
muninn/client/show.py
muninn/client/status.py
muninn/client/user.py
odin_api-0.7.6.data/scripts/authenticate.py
odin_api-0.7.6.data/scripts/cleanup.py
odin_api-0.7.6.data/scripts/create.py
odin_api-0.7.6.data/scripts/data.py
odin_api-0.7.6.data/scripts/events.py
odin_api-0.7.6.data/scripts/gpus.py
odin_api-0.7.6.data/scripts/logs.py
odin_api-0.7.6.data/scripts/ping.py
odin_api-0.7.6.data/scripts/push.py
odin_api-0.7.6.data/scripts/run.py
odin_api-0.7.6.data/scripts/show.py
odin_api-0.7.6.data/scripts/user.py
odin_api-0.7.6.dist-info/LICENSE
odin_api-0.7.6.dist-info/METADATA
odin_api-0.7.6.dist-info/NOTICE
odin_api-0.7.6.dist-info/WHEEL
odin_api-0.7.6.dist-info/entry_points.txt
odin_api-0.7.6.dist-info/top_level.txt
odin_api-0.7.6.dist-info/RECORD
